{
  "taskDefinitionArn": "arn:aws:ecs:ap-northeast-1:ACCOUNT_ID:task-definition/firepoker-task:1",
  "family": "firepoker-task",
  "taskRoleArn": "arn:aws:iam::ACCOUNT_ID:role/ecsTaskExecutionRole",
  "executionRoleArn": "arn:aws:iam::ACCOUNT_ID:role/ecsTaskExecutionRole",
  "networkMode": "awsvpc",
  "containerDefinitions": [
    {
      "name": "firepoker-app",
      "image": "ACCOUNT_ID.dkr.ecr.ap-northeast-1.amazonaws.com/firepoker:latest",
      "cpu": 512,
      "memory": 1024,
      "essential": true,
      "portMappings": [
        {
          "containerPort": 3000,
          "protocol": "tcp"
        }
      ],
      "environment": [
        {
          "name": "NODE_ENV",
          "value": "production"
        },
        {
          "name": "REDIS_HOST",
          "value": "firepoker-redis"
        },
        {
          "name": "REDIS_PORT",
          "value": "6379"
        }
      ],
      "secrets": [
        {
          "name": "NOTION_TOKEN",
          "valueFrom": "arn:aws:secretsmanager:ap-northeast-1:ACCOUNT_ID:secret:firepoker/notion-token"
        },
        {
          "name": "NOTION_PBI_DB_ID",
          "valueFrom": "arn:aws:secretsmanager:ap-northeast-1:ACCOUNT_ID:secret:firepoker/pbi-db-id"
        }
      ],
      "logConfiguration": {
        "logDriver": "awslogs",
        "options": {
          "awslogs-group": "/ecs/firepoker",
          "awslogs-region": "ap-northeast-1",
          "awslogs-stream-prefix": "app"
        }
      },
      "healthCheck": {
        "command": ["CMD-SHELL", "wget --no-verbose --tries=1 --spider http://localhost:3000/api/health || exit 1"],
        "interval": 30,
        "timeout": 5,
        "retries": 3,
        "startPeriod": 60
      }
    },
    {
      "name": "firepoker-redis",
      "image": "redis:7-alpine",
      "cpu": 256,
      "memory": 512,
      "essential": true,
      "command": [
        "redis-server",
        "--save",
        "",
        "--appendonly",
        "no"
      ],
      "portMappings": [
        {
          "containerPort": 6379,
          "protocol": "tcp"
        }
      ],
      "logConfiguration": {
        "logDriver": "awslogs",
        "options": {
          "awslogs-group": "/ecs/firepoker",
          "awslogs-region": "ap-northeast-1",
          "awslogs-stream-prefix": "redis"
        }
      },
      "healthCheck": {
        "command": ["CMD-SHELL", "redis-cli ping || exit 1"],
        "interval": 30,
        "timeout": 5,
        "retries": 3,
        "startPeriod": 30
      }
    }
  ],
  "requiresCompatibilities": ["FARGATE"],
  "cpu": "1024",
  "memory": "2048",
  "runtimePlatform": {
    "cpuArchitecture": "X86_64",
    "operatingSystemFamily": "LINUX"
  }
}
